spex_tequila.cp311-win_amd64.pyd
spex_tequila-1.0.0.dist-info/._PKG-INFO
spex_tequila-1.0.0.dist-info/LICENSE
spex_tequila-1.0.0.dist-info/METADATA
spex_tequila-1.0.0.dist-info/WHEEL
spex_tequila-1.0.0.dist-info/top_level.txt
spex_tequila-1.0.0.dist-info/RECORD
