Metadata-Version: 2.1
Name: spex-tequila
Version: 1.0.0
Summary: Expectation value computation module on sparse Pauli states for Tequila, implemented in C++ using Pybind11
Home-page: https://git.rz.uni-augsburg.de/qalg-a/spex
Author: Michael Lang
Author-email: lang-michi@t-online.de
Classifier: Programming Language :: Python :: 3
Classifier: Programming Language :: C++
Classifier: Operating System :: OS Independent
Classifier: License :: OSI Approved :: MIT License
Requires-Python: >=3.9
License-File: LICENSE
Requires-Dist: pybind11>=2.5.0
